mce_opik_adapter/__init__.py
mce_opik_adapter/adapter.py
mce_opik_adapter/metric_configuration.py
mce_opik_adapter/metric_test_case_creation.py
mce_opik_adapter/model_loader.py
mce_opik_adapter-0.1.3.dist-info/METADATA
mce_opik_adapter-0.1.3.dist-info/WHEEL
mce_opik_adapter-0.1.3.dist-info/entry_points.txt
mce_opik_adapter-0.1.3.dist-info/RECORD
