Metadata-Version: 2.4
Name: mce-opik-adapter
Version: 0.1.3
Summary: Opik integration adapter for Metrics Computation Engine
Project-URL: Homepage, https://github.com/agntcy/telemetry-hub
Project-URL: Repository, https://github.com/agntcy/telemetry-hub
Project-URL: Issues, https://github.com/agntcy/telemetry-hub/issues
Author: AGNTCY Telemetry Hub team
License-Expression: Apache-2.0
Classifier: Development Status :: 3 - Alpha
Classifier: Intended Audience :: Developers
Classifier: License :: OSI Approved :: Apache Software License
Classifier: Programming Language :: Python :: 3
Classifier: Programming Language :: Python :: 3.8
Classifier: Programming Language :: Python :: 3.9
Classifier: Programming Language :: Python :: 3.10
Classifier: Programming Language :: Python :: 3.11
Classifier: Programming Language :: Python :: 3.12
Classifier: Programming Language :: Python :: 3.13
Requires-Python: >=3.8
Requires-Dist: nltk
Requires-Dist: opik>=1.8.27
Requires-Dist: rouge-score
Provides-Extra: dev
Requires-Dist: black; extra == 'dev'
Requires-Dist: flake8; extra == 'dev'
Requires-Dist: mypy; extra == 'dev'
Requires-Dist: pytest; extra == 'dev'
Requires-Dist: pytest-cov; extra == 'dev'
